jupyverse_api/__init__.py
jupyverse_api/app/__init__.py
jupyverse_api/auth/__init__.py
jupyverse_api/auth/models.py
jupyverse_api/cli.py
jupyverse_api/contents/__init__.py
jupyverse_api/contents/models.py
jupyverse_api/exceptions.py
jupyverse_api/file_id/__init__.py
jupyverse_api/file_watcher/__init__.py
jupyverse_api/frontend/__init__.py
jupyverse_api/jupyterlab/__init__.py
jupyverse_api/kernel/__init__.py
jupyverse_api/kernels/__init__.py
jupyverse_api/kernels/models.py
jupyverse_api/lab/__init__.py
jupyverse_api/lab/lab.py
jupyverse_api/lab/page_config.py
jupyverse_api/login/__init__.py
jupyverse_api/main/__init__.py
jupyverse_api/nbconvert/__init__.py
jupyverse_api/notebook/__init__.py
jupyverse_api/py.typed
jupyverse_api/resource_usage/__init__.py
jupyverse_api/terminals/__init__.py
jupyverse_api/terminals/models.py
jupyverse_api/yjs/__init__.py
jupyverse_api/yjs/models.py
jupyverse_api-0.13.1.dist-info/licenses/COPYING.md
jupyverse_api-0.13.1.dist-info/WHEEL
jupyverse_api-0.13.1.dist-info/entry_points.txt
jupyverse_api-0.13.1.dist-info/METADATA
jupyverse_api-0.13.1.dist-info/RECORD
