Metadata-Version: 2.4
Name: jupyverse_api
Version: 0.13.1
Summary: The public API for Jupyverse
Keywords: jupyverse,api
Author: Jupyter Development Team
Author-email: Jupyter Development Team <jupyter@googlegroups.com>
License-Expression: BSD-3-Clause
License-File: COPYING.md
Classifier: Development Status :: 5 - Production/Stable
Classifier: Intended Audience :: Developers
Classifier: License :: OSI Approved :: BSD License
Classifier: Programming Language :: Python
Classifier: Programming Language :: Python :: 3.10
Classifier: Programming Language :: Python :: 3.11
Classifier: Programming Language :: Python :: 3.12
Classifier: Programming Language :: Python :: 3.13
Classifier: Programming Language :: Python :: 3.14
Classifier: Programming Language :: Python :: Implementation :: CPython
Classifier: Programming Language :: Python :: Implementation :: PyPy
Requires-Dist: pydantic>=2,<3
Requires-Dist: fastapi>=0.95.0,<1
Requires-Dist: fps>=0.5.7,<0.6.0
Requires-Dist: anyio>=4.9.0,<5
Requires-Dist: anyioutils>=0.7.4
Requires-Python: >=3.10
Project-URL: Source, https://github.com/jupyter-server/jupyverse/jupyverse_api
